pyfortinet/__init__.py
pyfortinet/exceptions.py
pyfortinet/settings.py
pyfortinet/fmg_api/__init__.py
pyfortinet/fmg_api/async_fmg.py
pyfortinet/fmg_api/async_fmgbase.py
pyfortinet/fmg_api/common.py
pyfortinet/fmg_api/dvmcmd.py
pyfortinet/fmg_api/dvmdb.py
pyfortinet/fmg_api/firewall.py
pyfortinet/fmg_api/fmg.py
pyfortinet/fmg_api/fmgbase.py
pyfortinet/fmg_api/pm_config_cli.py
pyfortinet/fmg_api/policy.py
pyfortinet/fmg_api/securityconsole.py
pyfortinet/fmg_api/task.py
pyfortinet-0.0.1.post2.dist-info/entry_points.txt
pyfortinet-0.0.1.post2.dist-info/WHEEL
pyfortinet-0.0.1.post2.dist-info/METADATA
pyfortinet-0.0.1.post2.dist-info/RECORD
