Metadata-Version: 2.1
Name: pyfortinet
Version: 0.0.1.post2
Summary: Fortinet Python library
Author-email: Viktor Kertesz <vkertesz2@gmail.com>
Requires-Python: >=3.9,<4
Classifier: License :: OSI Approved :: MIT License
Classifier: Operating System :: Microsoft :: Windows
Classifier: Operating System :: POSIX :: Linux
Classifier: Programming Language :: Python :: 3
Classifier: Topic :: System :: Networking
Requires-Dist: pydantic>2,<3
Requires-Dist: pydantic-settings
Requires-Dist: typer
Requires-Dist: requests==2.31.0
Requires-Dist: ruamel.yaml==0.17.20
Requires-Dist: more-itertools
Requires-Dist: rich ; extra == "all"
Requires-Dist: aiohttp ; extra == "all"
Requires-Dist: aiohttp ; extra == "async"
Requires-Dist: pytest-cov ; extra == "dev"
Requires-Dist: pytest ; extra == "dev"
Requires-Dist: pytest-async ; extra == "dev"
Requires-Dist: pytest-dependency ; extra == "dev"
Requires-Dist: flit ; extra == "dev"
Requires-Dist: invoke ; extra == "dev"
Requires-Dist: pre-commit ; extra == "dev"
Requires-Dist: ruff ; extra == "dev"
Requires-Dist: mkdocs ; extra == "dev"
Requires-Dist: mkdocs-material ; extra == "dev"
Requires-Dist: mkdocs-gen-files ; extra == "dev"
Requires-Dist: mkdocs-literate-nav ; extra == "dev"
Requires-Dist: mkdocs-section-index ; extra == "dev"
Requires-Dist: mkdocstrings ; extra == "dev"
Requires-Dist: mkdocstrings-python ; extra == "dev"
Requires-Dist: rich ; extra == "dev"
Requires-Dist: aiohttp ; extra == "dev"
Requires-Dist: rich ; extra == "rich"
Project-URL: Documentation, https://realvitya.github.io/pyfortinet/
Project-URL: Source, https://github.com/realvitya/pyfortinet
Provides-Extra: all
Provides-Extra: async
Provides-Extra: dev
Provides-Extra: rich
